eevent/__init__.py
eevent/py.typed
eevent-0.3.1.dist-info/METADATA
eevent-0.3.1.dist-info/WHEEL
eevent-0.3.1.dist-info/RECORD
