Metadata-Version: 2.3
Name: eevent
Version: 0.3.1
Summary: Asyncio Events
Author: Erik Soma
Author-email: stillusingirc@gmail.com
Requires-Python: >=3.12
Classifier: Programming Language :: Python :: 3
Classifier: Programming Language :: Python :: 3.12
Classifier: Programming Language :: Python :: 3.13
